pynput_recorder/__init__.py
pynput_recorder/actionlistener.py
pynput_recorder/actionrunner.py
pynput_recorder/comm.py
pynput_recorder/recorder.py
pynput_recorder-1.0.0.dist-info/LICENSE
pynput_recorder-1.0.0.dist-info/METADATA
pynput_recorder-1.0.0.dist-info/WHEEL
pynput_recorder-1.0.0.dist-info/top_level.txt
pynput_recorder-1.0.0.dist-info/RECORD
