Metadata-Version: 2.1
Name: pynput_recorder
Version: 1.0.0
Summary: pynput_recorder: Recorder GUI Application for pynput
Home-page: https://github.com/shigebeyond/pynput_recorder
Author: shigebeyond
Author-email: 772910474@qq.com
License: BSD
Classifier: Development Status :: 5 - Production/Stable
Classifier: Topic :: Software Development :: Libraries :: Python Modules
Classifier: Operating System :: POSIX :: Linux
Classifier: Operating System :: MacOS :: MacOS X
Classifier: Operating System :: Microsoft :: Windows
Classifier: Programming Language :: Python
Classifier: Programming Language :: Python :: 3.7
Classifier: Programming Language :: Python :: 3.8
Classifier: Programming Language :: Python :: 3.9
Requires-Python: >=3.6
License-File: LICENSE
Requires-Dist: pyutilb>=1.0.8
Requires-Dist: pynput>=1.7.7
